[{"key":4025,"data":{"name":"item 4025","description":"this is the item 4025"}},{"key":4037,"data":{"name":"item 4037","description":"this is the item 4037"}},{"key":4048,"data":{"name":"item 4048","description":"this is the item 4048"}},{"key":4055,"data":{"name":"item 4055","description":"this is the item 4055"}},{"key":4060,"data":{"name":"item 4060","description":"this is the item 4060"}},{"key":4070,"data":{"name":"item 4070","description":"this is the item 4070"}},{"key":4080,"data":{"name":"item 4080","description":"this is the item 4080"}},{"key":4084,"data":{"name":"item 4084","description":"this is the item 4084"}},{"key":4086,"data":{"name":"item 4086","description":"this is the item 4086"}},{"key":4087,"data":{"name":"item 4087","description":"this is the item 4087"}},{"key":4122,"data":{"name":"item 4122","description":"this is the item 4122"}},{"key":4137,"data":{"name":"item 4137","description":"this is the item 4137"}},{"key":4180,"data":{"name":"item 4180","description":"this is the item 4180"}},{"key":4183,"data":{"name":"item 4183","description":"this is the item 4183"}},{"key":4191,"data":{"name":"item 4191","description":"this is the item 4191"}},{"key":4205,"data":{"name":"item 4205","description":"this is the item 4205"}},{"key":4246,"data":{"name":"item 4246","description":"this is the item 4246"}},{"key":4273,"data":{"name":"item 4273","description":"this is the item 4273"}},{"key":4280,"data":{"name":"item 4280","description":"this is the item 4280"}},{"key":4290,"data":{"name":"item 4290","description":"this is the item 4290"}},{"key":4299,"data":{"name":"item 4299","description":"this is the item 4299"}},{"key":4330,"data":{"name":"item 4330","description":"this is the item 4330"}},{"key":4357,"data":{"name":"item 4357","description":"this is the item 4357"}},{"key":4375,"data":{"name":"item 4375","description":"this is the item 4375"}},{"key":4446,"data":{"name":"item 4446","description":"this is the item 4446"}},{"key":4481,"data":{"name":"item 4481","description":"this is the item 4481"}},{"key":4550,"data":{"name":"item 4550","description":"this is the item 4550"}},{"key":4569,"data":{"name":"item 4569","description":"this is the item 4569"}},{"key":4586,"data":{"name":"item 4586","description":"this is the item 4586"}},{"key":4591,"data":{"name":"item 4591","description":"this is the item 4591"}},{"key":4611,"data":{"name":"item 4611","description":"this is the item 4611"}},{"key":4658,"data":{"name":"item 4658","description":"this is the item 4658"}},{"key":4665,"data":{"name":"item 4665","description":"this is the item 4665"}},{"key":4690,"data":{"name":"item 4690","description":"this is the item 4690"}},{"key":4697,"data":{"name":"item 4697","description":"this is the item 4697"}},{"key":4705,"data":{"name":"item 4705","description":"this is the item 4705"}},{"key":4709,"data":{"name":"item 4709","description":"this is the item 4709"}},{"key":4712,"data":{"name":"item 4712","description":"this is the item 4712"}},{"key":4719,"data":{"name":"item 4719","description":"this is the item 4719"}},{"key":4722,"data":{"name":"item 4722","description":"this is the item 4722"}},{"key":4739,"data":{"name":"item 4739","description":"this is the item 4739"}},{"key":4758,"data":{"name":"item 4758","description":"this is the item 4758"}},{"key":4784,"data":{"name":"item 4784","description":"this is the item 4784"}},{"key":4813,"data":{"name":"item 4813","description":"this is the item 4813"}},{"key":4849,"data":{"name":"item 4849","description":"this is the item 4849"}},{"key":4888,"data":{"name":"item 4888","description":"this is the item 4888"}},{"key":4912,"data":{"name":"item 4912","description":"this is the item 4912"}},{"key":4940,"data":{"name":"item 4940","description":"this is the item 4940"}},{"key":4942,"data":{"name":"item 4942","description":"this is the item 4942"}},{"key":4986,"data":{"name":"item 4986","description":"this is the item 4986"}},{"key":4988,"data":{"name":"item 4988","description":"this is the item 4988"}},{"key":4997,"data":{"name":"item 4997","description":"this is the item 4997"}}]